COPYING
LICENSES
MANIFEST.in
README.txt
distribute_setup.py
setup-site.cfg
setup.cfg
setup.py
Orange/__init__.py
Orange/core.py
Orange/version.py
Orange.egg-info/PKG-INFO
Orange.egg-info/SOURCES.txt
Orange.egg-info/dependency_links.txt
Orange.egg-info/entry_points.txt
Orange.egg-info/not-zip-safe
Orange.egg-info/requires.txt
Orange.egg-info/top_level.txt
Orange/OrangeCanvas/WidgetTabs.txt
Orange/OrangeCanvas/__init__.py
Orange/OrangeCanvas/config.py
Orange/OrangeCanvas/main.py
Orange/OrangeCanvas/orngCanvas.pyw
Orange/OrangeCanvas/orngCanvasItems.py
Orange/OrangeCanvas/orngDlgs.py
Orange/OrangeCanvas/orngDoc.py
Orange/OrangeCanvas/orngGui.py
Orange/OrangeCanvas/orngHelp.py
Orange/OrangeCanvas/orngHistory.py
Orange/OrangeCanvas/orngOutput.py
Orange/OrangeCanvas/orngRegistry.py
Orange/OrangeCanvas/orngSignalManager.py
Orange/OrangeCanvas/orngTabs.py
Orange/OrangeCanvas/orngView.py
Orange/OrangeCanvas/resources.py
Orange/OrangeCanvas/application/__init__.py
Orange/OrangeCanvas/application/aboutdialog.py
Orange/OrangeCanvas/application/addons.py
Orange/OrangeCanvas/application/application.py
Orange/OrangeCanvas/application/canvasmain.py
Orange/OrangeCanvas/application/canvastooldock.py
Orange/OrangeCanvas/application/outputview.py
Orange/OrangeCanvas/application/schemeinfo.py
Orange/OrangeCanvas/application/settings.py
Orange/OrangeCanvas/application/welcomedialog.py
Orange/OrangeCanvas/application/widgettoolbox.py
Orange/OrangeCanvas/application/tests/__init__.py
Orange/OrangeCanvas/application/tests/test_canvastooldock.py
Orange/OrangeCanvas/application/tests/test_outputview.py
Orange/OrangeCanvas/application/tests/test_schemeinfo.py
Orange/OrangeCanvas/application/tests/test_settings.py
Orange/OrangeCanvas/application/tests/test_welcomedialog.py
Orange/OrangeCanvas/application/tests/test_widgettoolbox.py
Orange/OrangeCanvas/application/tutorials/005-func-genom-workshop.ows
Orange/OrangeCanvas/application/tutorials/250-tree-scatterplot.ows
Orange/OrangeCanvas/application/tutorials/310-clustering.ows
Orange/OrangeCanvas/application/tutorials/450-cross-validation.ows
Orange/OrangeCanvas/application/tutorials/__init__.py
Orange/OrangeCanvas/canvas/__init__.py
