Metadata-Version: 2.0
Name: Orange
Version: 2.7.8
Summary: Orange, a component-based data mining framework.
Home-page: http://orange.biolab.si/
Author: Bioinformatics Laboratory, FRI UL
Author-email: contact@orange.biolab.si
License: GPLv3
Download-URL: https://bitbucket.org/biolab/orange/downloads
Keywords: data mining,machine learning,artificial intelligence
Platform: UNKNOWN
Classifier: Development Status :: 4 - Beta
Classifier: Environment :: X11 Applications :: Qt
Classifier: Environment :: Console
Classifier: Environment :: Plugins
Classifier: Programming Language :: Python
Classifier: License :: OSI Approved :: GNU General Public License v3 or later (GPLv3+)
Classifier: Operating System :: POSIX
Classifier: Operating System :: Microsoft :: Windows
Classifier: Topic :: Scientific/Engineering :: Artificial Intelligence
Classifier: Topic :: Scientific/Engineering :: Visualization
Classifier: Topic :: Software Development :: Libraries :: Python Modules
Classifier: Intended Audience :: Education
Classifier: Intended Audience :: Science/Research
Classifier: Intended Audience :: Developers
Requires-Dist: setuptools
Requires-Dist: numpy
Requires-Dist: scipy
Provides-Extra: GUI
Requires-Dist: PyQt4; extra == 'GUI'
Requires-Dist: PyQwt; extra == 'GUI'
Provides-Extra: reST
Requires-Dist: numpydoc; extra == 'reST'
